[
  {
    "Date": "2024-01-29",
    "Year": "2024",
    "Month": "2024-01",
    "SignUps_Accepted": 0,
    "FirstUploads_Accepted": 0,
    "PaidSubscribers_Accepted": 1,
    "SignUp_Details": "",
    "Upload_Details": "",
    "Paid_Details": "Luca Fixy <luca.fixy@soclecollections.com>",
    "LastUpdated": "2026-06-17 15:40:20"
  },
  {
    "Date": "2024-01-31",
    "Year": "2024",
    "Month": "2024-01",
    "SignUps_Accepted": 0,
    "FirstUploads_Accepted": 0,
    "PaidSubscribers_Accepted": 1,
    "SignUp_Details": "",
    "Upload_Details": "",
    "Paid_Details": "Lunas <vasili@lunas.pro>",
    "LastUpdated": "2026-06-17 15:40:20"
  },
  {
    "Date": "2024-02-01",
    "Year": "2024",
    "Month": "2024-02",
    "SignUps_Accepted": 0,
    "FirstUploads_Accepted": 0,
    "PaidSubscribers_Accepted": 1,
    "SignUp_Details": "",
    "Upload_Details": "",
    "Paid_Details": "BeyondCAD <erin@beyondcad.com>",
    "LastUpdated": "2026-06-17 15:40:20"
  },
  {
    "Date": "2024-02-03",
    "Year": "2024",
    "Month": "2024-02",
    "SignUps_Accepted": 0,
    "FirstUploads_Accepted": 0,
    "PaidSubscribers_Accepted": 1,
    "SignUp_Details": "",
    "Upload_Details": "",
    "Paid_Details": "Susan Budnik <sbudnik@hntb.com>",
    "LastUpdated": "2026-06-17 15:40:20"
  },
  {
    "Date": "2024-02-07",
    "Year": "2024",
    "Month": "2024-02",
    "SignUps_Accepted": 0,
    "FirstUploads_Accepted": 0,
    "PaidSubscribers_Accepted": 2,
    "SignUp_Details": "",
    "Upload_Details": "",
    "Paid_Details": "Clemens Hofmann <conquista.games@yandex.com>; Scott Futryk <scott@anywhereanytime.io>",
    "LastUpdated": "2026-06-17 15:40:20"
  },
  {
    "Date": "2024-02-09",
    "Year": "2024",
    "Month": "2024-02",
    "SignUps_Accepted": 0,
    "FirstUploads_Accepted": 0,
    "PaidSubscribers_Accepted": 3,
    "SignUp_Details": "",
    "Upload_Details": "",
    "Paid_Details": "John Harding 1 <eagledemo@invicara.com>; John Harding 2 <eagleoxagon@invicara.com>; John Harding 3 <eagledev@invicara.com>",
    "LastUpdated": "2026-06-17 15:40:20"
  },
  {
    "Date": "2024-02-10",
    "Year": "2024",
    "Month": "2024-02",
    "SignUps_Accepted": 0,
    "FirstUploads_Accepted": 0,
    "PaidSubscribers_Accepted": 1,
    "SignUp_Details": "",
    "Upload_Details": "",
    "Paid_Details": "Renan Abreu <renan@grpempreendimentos.com.br>",
    "LastUpdated": "2026-06-17 15:40:20"
  },
  {
    "Date": "2024-02-13",
    "Year": "2024",
    "Month": "2024-02",
    "SignUps_Accepted": 0,
    "FirstUploads_Accepted": 0,
    "PaidSubscribers_Accepted": 1,
    "SignUp_Details": "",
    "Upload_Details": "",
    "Paid_Details": "Marcio Neves <marcio.neves@hotmail.com>",
    "LastUpdated": "2026-06-17 15:40:20"
  },
  {
    "Date": "2024-02-16",
    "Year": "2024",
    "Month": "2024-02",
    "SignUps_Accepted": 0,
    "FirstUploads_Accepted": 0,
    "PaidSubscribers_Accepted": 2,
    "SignUp_Details": "",
    "Upload_Details": "",
    "Paid_Details": "chateauz <explore@chateauz.io>; kathyu.168 <kathleen.yu@nudgyt.com>",
    "LastUpdated": "2026-06-17 15:40:20"
  },
  {
    "Date": "2024-02-21",
    "Year": "2024",
    "Month": "2024-02",
    "SignUps_Accepted": 0,
    "FirstUploads_Accepted": 0,
    "PaidSubscribers_Accepted": 1,
    "SignUp_Details": "",
    "Upload_Details": "",
    "Paid_Details": "TrastPixel <greensteel@raumvisionen.de>",
    "LastUpdated": "2026-06-17 15:40:20"
  },
  {
    "Date": "2024-02-22",
    "Year": "2024",
    "Month": "2024-02",
    "SignUps_Accepted": 0,
    "FirstUploads_Accepted": 0,
    "PaidSubscribers_Accepted": 1,
    "SignUp_Details": "",
    "Upload_Details": "",
    "Paid_Details": "vconquest <brenden382@gmail.com>",
    "LastUpdated": "2026-06-17 15:40:20"
  },
  {
    "Date": "2024-02-25",
    "Year": "2024",
    "Month": "2024-02",
    "SignUps_Accepted": 0,
    "FirstUploads_Accepted": 0,
    "PaidSubscribers_Accepted": 1,
    "SignUp_Details": "",
    "Upload_Details": "",
    "Paid_Details": "futureact <info@futureact.eu>",
    "LastUpdated": "2026-06-17 15:40:20"
  },
  {
    "Date": "2024-03-13",
    "Year": "2024",
    "Month": "2024-03",
    "SignUps_Accepted": 0,
    "FirstUploads_Accepted": 0,
    "PaidSubscribers_Accepted": 1,
    "SignUp_Details": "",
    "Upload_Details": "",
    "Paid_Details": "3DHomeMedia <info@3dhm.com>",
    "LastUpdated": "2026-06-17 15:40:20"
  },
  {
    "Date": "2024-03-14",
    "Year": "2024",
    "Month": "2024-03",
    "SignUps_Accepted": 0,
    "FirstUploads_Accepted": 0,
    "PaidSubscribers_Accepted": 1,
    "SignUp_Details": "",
    "Upload_Details": "",
    "Paid_Details": "RaumVisionen <j.dreyer@raumvisionen.de>",
    "LastUpdated": "2026-06-17 15:40:20"
  },
  {
    "Date": "2024-03-26",
    "Year": "2024",
    "Month": "2024-03",
    "SignUps_Accepted": 0,
    "FirstUploads_Accepted": 0,
    "PaidSubscribers_Accepted": 1,
    "SignUp_Details": "",
    "Upload_Details": "",
    "Paid_Details": "JanRucil <rucil.jan@gmail.com>",
    "LastUpdated": "2026-06-17 15:40:20"
  },
  {
    "Date": "2024-04-22",
    "Year": "2024",
    "Month": "2024-04",
    "SignUps_Accepted": 0,
    "FirstUploads_Accepted": 0,
    "PaidSubscribers_Accepted": 2,
    "SignUp_Details": "",
    "Upload_Details": "",
    "Paid_Details": "Klaris <klaris@solidwave.co.uk>; smudgy67 <smudgy67@msn.com>",
    "LastUpdated": "2026-06-17 15:40:20"
  },
  {
    "Date": "2024-04-26",
    "Year": "2024",
    "Month": "2024-04",
    "SignUps_Accepted": 0,
    "FirstUploads_Accepted": 0,
    "PaidSubscribers_Accepted": 1,
    "SignUp_Details": "",
    "Upload_Details": "",
    "Paid_Details": "looore <lorenzoantonucci91@gmail.com>",
    "LastUpdated": "2026-06-17 15:40:20"
  },
  {
    "Date": "2024-05-18",
    "Year": "2024",
    "Month": "2024-05",
    "SignUps_Accepted": 0,
    "FirstUploads_Accepted": 0,
    "PaidSubscribers_Accepted": 1,
    "SignUp_Details": "",
    "Upload_Details": "",
    "Paid_Details": "adeeMWX <aditya@metaworldx.com>",
    "LastUpdated": "2026-06-17 15:40:20"
  },
  {
    "Date": "2024-05-25",
    "Year": "2024",
    "Month": "2024-05",
    "SignUps_Accepted": 0,
    "FirstUploads_Accepted": 0,
    "PaidSubscribers_Accepted": 1,
    "SignUp_Details": "",
    "Upload_Details": "",
    "Paid_Details": "WeberMassivhaus <weber@raumvisionen.com>",
    "LastUpdated": "2026-06-17 15:40:20"
  },
  {
    "Date": "2024-05-30",
    "Year": "2024",
    "Month": "2024-05",
    "SignUps_Accepted": 0,
    "FirstUploads_Accepted": 0,
    "PaidSubscribers_Accepted": 1,
    "SignUp_Details": "",
    "Upload_Details": "",
    "Paid_Details": "JosePareja <jpareja.arq@gmail.com>",
    "LastUpdated": "2026-06-17 15:40:20"
  },
  {
    "Date": "2024-06-17",
    "Year": "2024",
    "Month": "2024-06",
    "SignUps_Accepted": 0,
    "FirstUploads_Accepted": 0,
    "PaidSubscribers_Accepted": 1,
    "SignUp_Details": "",
    "Upload_Details": "",
    "Paid_Details": "Dev <unreal@molotovcocktail.tv>",
    "LastUpdated": "2026-06-17 15:40:20"
  },
  {
    "Date": "2024-07-12",
    "Year": "2024",
    "Month": "2024-07",
    "SignUps_Accepted": 0,
    "FirstUploads_Accepted": 0,
    "PaidSubscribers_Accepted": 1,
    "SignUp_Details": "",
    "Upload_Details": "",
    "Paid_Details": "Comercial-Carozzo <rodrigo@carozzo.com.br>",
    "LastUpdated": "2026-06-17 15:40:20"
  },
  {
    "Date": "2024-07-14",
    "Year": "2024",
    "Month": "2024-07",
    "SignUps_Accepted": 0,
    "FirstUploads_Accepted": 0,
    "PaidSubscribers_Accepted": 1,
    "SignUp_Details": "",
    "Upload_Details": "",
    "Paid_Details": "Mile80 <team@mile80.com>",
    "LastUpdated": "2026-06-17 15:40:20"
  },
  {
    "Date": "2024-07-31",
    "Year": "2024",
    "Month": "2024-07",
    "SignUps_Accepted": 0,
    "FirstUploads_Accepted": 0,
    "PaidSubscribers_Accepted": 1,
    "SignUp_Details": "",
    "Upload_Details": "",
    "Paid_Details": "CravingDigital <admin@cravingdigital.com>",
    "LastUpdated": "2026-06-17 15:40:20"
  },
  {
    "Date": "2024-08-15",
    "Year": "2024",
    "Month": "2024-08",
    "SignUps_Accepted": 0,
    "FirstUploads_Accepted": 0,
    "PaidSubscribers_Accepted": 1,
    "SignUp_Details": "",
    "Upload_Details": "",
    "Paid_Details": "XR-CN3 <ue@cn3.dk>",
    "LastUpdated": "2026-06-17 15:40:20"
  },
  {
    "Date": "2024-08-16",
    "Year": "2024",
    "Month": "2024-08",
    "SignUps_Accepted": 0,
    "FirstUploads_Accepted": 0,
    "PaidSubscribers_Accepted": 1,
    "SignUp_Details": "",
    "Upload_Details": "",
    "Paid_Details": "Spine3D <mike@s3d.net>",
    "LastUpdated": "2026-06-17 15:40:20"
  },
  {
    "Date": "2024-08-23",
    "Year": "2024",
    "Month": "2024-08",
    "SignUps_Accepted": 0,
    "FirstUploads_Accepted": 0,
    "PaidSubscribers_Accepted": 1,
    "SignUp_Details": "",
    "Upload_Details": "",
    "Paid_Details": "AdminAMGI <pixelstreaming@amgistudios.com>",
    "LastUpdated": "2026-06-17 15:40:20"
  },
  {
    "Date": "2024-09-07",
    "Year": "2024",
    "Month": "2024-09",
    "SignUps_Accepted": 0,
    "FirstUploads_Accepted": 0,
    "PaidSubscribers_Accepted": 1,
    "SignUp_Details": "",
    "Upload_Details": "",
    "Paid_Details": "anythinkworld <athao@anythinklibraries.org>",
    "LastUpdated": "2026-06-17 15:40:20"
  },
  {
    "Date": "2024-09-12",
    "Year": "2024",
    "Month": "2024-09",
    "SignUps_Accepted": 0,
    "FirstUploads_Accepted": 0,
    "PaidSubscribers_Accepted": 1,
    "SignUp_Details": "",
    "Upload_Details": "",
    "Paid_Details": "steved <steve@rupture.mt>",
    "LastUpdated": "2026-06-17 15:40:20"
  },
  {
    "Date": "2024-10-16",
    "Year": "2024",
    "Month": "2024-10",
    "SignUps_Accepted": 0,
    "FirstUploads_Accepted": 0,
    "PaidSubscribers_Accepted": 1,
    "SignUp_Details": "",
    "Upload_Details": "",
    "Paid_Details": "MileleMuseum <info@milele.space>",
    "LastUpdated": "2026-06-17 15:40:20"
  },
  {
    "Date": "2024-11-19",
    "Year": "2024",
    "Month": "2024-11",
    "SignUps_Accepted": 0,
    "FirstUploads_Accepted": 0,
    "PaidSubscribers_Accepted": 2,
    "SignUp_Details": "",
    "Upload_Details": "",
    "Paid_Details": "eagle@raumvisionen.de <eagle@raumvisionen.de>; jena@raumvisionen.de <jena@raumvisionen.de>",
    "LastUpdated": "2026-06-17 15:40:20"
  },
  {
    "Date": "2024-11-21",
    "Year": "2024",
    "Month": "2024-11",
    "SignUps_Accepted": 0,
    "FirstUploads_Accepted": 0,
    "PaidSubscribers_Accepted": 1,
    "SignUp_Details": "",
    "Upload_Details": "",
    "Paid_Details": "justin@newoodtechnology.com <justin@newoodtechnology.com>",
    "LastUpdated": "2026-06-17 15:40:20"
  },
  {
    "Date": "2024-11-26",
    "Year": "2024",
    "Month": "2024-11",
    "SignUps_Accepted": 0,
    "FirstUploads_Accepted": 0,
    "PaidSubscribers_Accepted": 1,
    "SignUp_Details": "",
    "Upload_Details": "",
    "Paid_Details": "k.bushtevich@lunas.pro <k.bushtevich@lunas.pro>",
    "LastUpdated": "2026-06-17 15:40:20"
  },
  {
    "Date": "2024-12-04",
    "Year": "2024",
    "Month": "2024-12",
    "SignUps_Accepted": 0,
    "FirstUploads_Accepted": 0,
    "PaidSubscribers_Accepted": 1,
    "SignUp_Details": "",
    "Upload_Details": "",
    "Paid_Details": "SpaceForm <it@spaceform.io>",
    "LastUpdated": "2026-06-17 15:40:20"
  },
  {
    "Date": "2024-12-05",
    "Year": "2024",
    "Month": "2024-12",
    "SignUps_Accepted": 0,
    "FirstUploads_Accepted": 0,
    "PaidSubscribers_Accepted": 1,
    "SignUp_Details": "",
    "Upload_Details": "",
    "Paid_Details": "stevef334@hotmail.com <stevef334@hotmail.com>",
    "LastUpdated": "2026-06-17 15:40:20"
  },
  {
    "Date": "2024-12-10",
    "Year": "2024",
    "Month": "2024-12",
    "SignUps_Accepted": 0,
    "FirstUploads_Accepted": 0,
    "PaidSubscribers_Accepted": 1,
    "SignUp_Details": "",
    "Upload_Details": "",
    "Paid_Details": "cheyul@cheyul.com <cheyul@cheyul.com>",
    "LastUpdated": "2026-06-17 15:40:20"
  },
  {
    "Date": "2024-12-30",
    "Year": "2024",
    "Month": "2024-12",
    "SignUps_Accepted": 0,
    "FirstUploads_Accepted": 0,
    "PaidSubscribers_Accepted": 1,
    "SignUp_Details": "",
    "Upload_Details": "",
    "Paid_Details": "Andrei <andrei@warped-studios.co.uk>",
    "LastUpdated": "2026-06-17 15:40:20"
  },
  {
    "Date": "2024-12-31",
    "Year": "2024",
    "Month": "2024-12",
    "SignUps_Accepted": 0,
    "FirstUploads_Accepted": 0,
    "PaidSubscribers_Accepted": 1,
    "SignUp_Details": "",
    "Upload_Details": "",
    "Paid_Details": "nudgyt01 <nudgyt01@gmail.com>",
    "LastUpdated": "2026-06-17 15:40:20"
  },
  {
    "Date": "2025-01-06",
    "Year": "2025",
    "Month": "2025-01",
    "SignUps_Accepted": 0,
    "FirstUploads_Accepted": 0,
    "PaidSubscribers_Accepted": 1,
    "SignUp_Details": "",
    "Upload_Details": "",
    "Paid_Details": "_eagle_ <eagledstreaming@gmail.com>",
    "LastUpdated": "2026-06-17 15:40:20"
  },
  {
    "Date": "2025-01-07",
    "Year": "2025",
    "Month": "2025-01",
    "SignUps_Accepted": 0,
    "FirstUploads_Accepted": 0,
    "PaidSubscribers_Accepted": 1,
    "SignUp_Details": "",
    "Upload_Details": "",
    "Paid_Details": "ryan.lever@swiftmarketingsolutions.co.uk <ryan.lever@swiftmarketingsolutions.co.uk>",
    "LastUpdated": "2026-06-17 15:40:20"
  },
  {
    "Date": "2025-01-16",
    "Year": "2025",
    "Month": "2025-01",
    "SignUps_Accepted": 0,
    "FirstUploads_Accepted": 0,
    "PaidSubscribers_Accepted": 1,
    "SignUp_Details": "",
    "Upload_Details": "",
    "Paid_Details": "PetrosDD <petrosdedoncker@gmail.com>",
    "LastUpdated": "2026-06-17 15:40:20"
  },
  {
    "Date": "2025-01-17",
    "Year": "2025",
    "Month": "2025-01",
    "SignUps_Accepted": 0,
    "FirstUploads_Accepted": 0,
    "PaidSubscribers_Accepted": 1,
    "SignUp_Details": "",
    "Upload_Details": "",
    "Paid_Details": "Hamilshred <mark@asano.app>",
    "LastUpdated": "2026-06-17 15:40:20"
  },
  {
    "Date": "2025-02-03",
    "Year": "2025",
    "Month": "2025-02",
    "SignUps_Accepted": 0,
    "FirstUploads_Accepted": 0,
    "PaidSubscribers_Accepted": 1,
    "SignUp_Details": "",
    "Upload_Details": "",
    "Paid_Details": "sasan <sasan1360@gmail.com>",
    "LastUpdated": "2026-06-17 15:40:20"
  },
  {
    "Date": "2025-02-21",
    "Year": "2025",
    "Month": "2025-02",
    "SignUps_Accepted": 0,
    "FirstUploads_Accepted": 0,
    "PaidSubscribers_Accepted": 1,
    "SignUp_Details": "",
    "Upload_Details": "",
    "Paid_Details": "j.harwell@renderfoundry.com <j.harwell@renderfoundry.com>",
    "LastUpdated": "2026-06-17 15:40:20"
  },
  {
    "Date": "2025-02-25",
    "Year": "2025",
    "Month": "2025-02",
    "SignUps_Accepted": 0,
    "FirstUploads_Accepted": 0,
    "PaidSubscribers_Accepted": 1,
    "SignUp_Details": "",
    "Upload_Details": "",
    "Paid_Details": "futuregenerationproductions <media@futuregenerationproductions.com>",
    "LastUpdated": "2026-06-17 15:40:20"
  },
  {
    "Date": "2025-02-28",
    "Year": "2025",
    "Month": "2025-02",
    "SignUps_Accepted": 0,
    "FirstUploads_Accepted": 0,
    "PaidSubscribers_Accepted": 1,
    "SignUp_Details": "",
    "Upload_Details": "",
    "Paid_Details": "cbre <cbre@imerza.com>",
    "LastUpdated": "2026-06-17 15:40:20"
  },
  {
    "Date": "2025-03-03",
    "Year": "2025",
    "Month": "2025-03",
    "SignUps_Accepted": 0,
    "FirstUploads_Accepted": 0,
    "PaidSubscribers_Accepted": 1,
    "SignUp_Details": "",
    "Upload_Details": "",
    "Paid_Details": "carl.hoemke@gmail.com <carl.hoemke@gmail.com>",
    "LastUpdated": "2026-06-17 15:40:20"
  },
  {
    "Date": "2025-03-07",
    "Year": "2025",
    "Month": "2025-03",
    "SignUps_Accepted": 0,
    "FirstUploads_Accepted": 0,
    "PaidSubscribers_Accepted": 1,
    "SignUp_Details": "",
    "Upload_Details": "",
    "Paid_Details": "entwicklung@tarakos.de <entwicklung@tarakos.de>",
    "LastUpdated": "2026-06-17 15:40:20"
  },
  {
    "Date": "2025-03-13",
    "Year": "2025",
    "Month": "2025-03",
    "SignUps_Accepted": 0,
    "FirstUploads_Accepted": 0,
    "PaidSubscribers_Accepted": 1,
    "SignUp_Details": "",
    "Upload_Details": "",
    "Paid_Details": "david@next-home.pro <david@next-home.pro>",
    "LastUpdated": "2026-06-17 15:40:20"
  },
  {
    "Date": "2025-03-19",
    "Year": "2025",
    "Month": "2025-03",
    "SignUps_Accepted": 0,
    "FirstUploads_Accepted": 0,
    "PaidSubscribers_Accepted": 1,
    "SignUp_Details": "",
    "Upload_Details": "",
    "Paid_Details": "f.filliat@studiopiranese.com <f.filliat@studiopiranese.com>",
    "LastUpdated": "2026-06-17 15:40:20"
  },
  {
    "Date": "2025-03-20",
    "Year": "2025",
    "Month": "2025-03",
    "SignUps_Accepted": 0,
    "FirstUploads_Accepted": 0,
    "PaidSubscribers_Accepted": 1,
    "SignUp_Details": "",
    "Upload_Details": "",
    "Paid_Details": "sebastian.suarez@kyonxr.com <sebastian.suarez@kyonxr.com>",
    "LastUpdated": "2026-06-17 15:40:20"
  },
  {
    "Date": "2025-03-26",
    "Year": "2025",
    "Month": "2025-03",
    "SignUps_Accepted": 0,
    "FirstUploads_Accepted": 0,
    "PaidSubscribers_Accepted": 1,
    "SignUp_Details": "",
    "Upload_Details": "",
    "Paid_Details": "juan@vanishingpoint3d.com <juan@vanishingpoint3d.com>",
    "LastUpdated": "2026-06-17 15:40:20"
  },
  {
    "Date": "2025-03-27",
    "Year": "2025",
    "Month": "2025-03",
    "SignUps_Accepted": 0,
    "FirstUploads_Accepted": 0,
    "PaidSubscribers_Accepted": 1,
    "SignUp_Details": "",
    "Upload_Details": "",
    "Paid_Details": "lanterne_digitale <info@lanternedigitale.com>",
    "LastUpdated": "2026-06-17 15:40:20"
  },
  {
    "Date": "2025-04-02",
    "Year": "2025",
    "Month": "2025-04",
    "SignUps_Accepted": 0,
    "FirstUploads_Accepted": 0,
    "PaidSubscribers_Accepted": 1,
    "SignUp_Details": "",
    "Upload_Details": "",
    "Paid_Details": "milton@movipar.com.br <milton@movipar.com.br>",
    "LastUpdated": "2026-06-17 15:40:20"
  },
  {
    "Date": "2025-04-03",
    "Year": "2025",
    "Month": "2025-04",
    "SignUps_Accepted": 0,
    "FirstUploads_Accepted": 0,
    "PaidSubscribers_Accepted": 1,
    "SignUp_Details": "",
    "Upload_Details": "",
    "Paid_Details": "studio@bolton-menk.com <studio@bolton-menk.com>",
    "LastUpdated": "2026-06-17 15:40:20"
  },
  {
    "Date": "2025-04-08",
    "Year": "2025",
    "Month": "2025-04",
    "SignUps_Accepted": 0,
    "FirstUploads_Accepted": 0,
    "PaidSubscribers_Accepted": 1,
    "SignUp_Details": "",
    "Upload_Details": "",
    "Paid_Details": "nadia <nadia@nudgyt.com>",
    "LastUpdated": "2026-06-17 15:40:20"
  },
  {
    "Date": "2025-04-11",
    "Year": "2025",
    "Month": "2025-04",
    "SignUps_Accepted": 0,
    "FirstUploads_Accepted": 0,
    "PaidSubscribers_Accepted": 1,
    "SignUp_Details": "",
    "Upload_Details": "",
    "Paid_Details": "brian@beyondcad.com <brian@beyondcad.com>",
    "LastUpdated": "2026-06-17 15:40:20"
  },
  {
    "Date": "2025-04-16",
    "Year": "2025",
    "Month": "2025-04",
    "SignUps_Accepted": 0,
    "FirstUploads_Accepted": 0,
    "PaidSubscribers_Accepted": 1,
    "SignUp_Details": "",
    "Upload_Details": "",
    "Paid_Details": "amministrazione@fattoriavittadini.it <amministrazione@fattoriavittadini.it>",
    "LastUpdated": "2026-06-17 15:40:20"
  },
  {
    "Date": "2025-04-20",
    "Year": "2025",
    "Month": "2025-04",
    "SignUps_Accepted": 0,
    "FirstUploads_Accepted": 0,
    "PaidSubscribers_Accepted": 1,
    "SignUp_Details": "",
    "Upload_Details": "",
    "Paid_Details": "ehsanaleahmad1359@yahoo.com <ehsanaleahmad1359@yahoo.com>",
    "LastUpdated": "2026-06-17 15:40:20"
  },
  {
    "Date": "2025-04-23",
    "Year": "2025",
    "Month": "2025-04",
    "SignUps_Accepted": 0,
    "FirstUploads_Accepted": 0,
    "PaidSubscribers_Accepted": 1,
    "SignUp_Details": "",
    "Upload_Details": "",
    "Paid_Details": "blakevictor <blake.victor@rolling7graphics.com>",
    "LastUpdated": "2026-06-17 15:40:20"
  },
  {
    "Date": "2025-04-25",
    "Year": "2025",
    "Month": "2025-04",
    "SignUps_Accepted": 0,
    "FirstUploads_Accepted": 0,
    "PaidSubscribers_Accepted": 1,
    "SignUp_Details": "",
    "Upload_Details": "",
    "Paid_Details": "it@powdermountain.com <it@powdermountain.com>",
    "LastUpdated": "2026-06-17 15:40:20"
  },
  {
    "Date": "2025-05-15",
    "Year": "2025",
    "Month": "2025-05",
    "SignUps_Accepted": 0,
    "FirstUploads_Accepted": 0,
    "PaidSubscribers_Accepted": 1,
    "SignUp_Details": "",
    "Upload_Details": "",
    "Paid_Details": "tim@the-boundary.com <tim@the-boundary.com>",
    "LastUpdated": "2026-06-17 15:40:20"
  },
  {
    "Date": "2025-05-23",
    "Year": "2025",
    "Month": "2025-05",
    "SignUps_Accepted": 0,
    "FirstUploads_Accepted": 0,
    "PaidSubscribers_Accepted": 1,
    "SignUp_Details": "",
    "Upload_Details": "",
    "Paid_Details": "kornel.meszaros.km@gmail.com <kornel.meszaros.km@gmail.com>",
    "LastUpdated": "2026-06-17 15:40:20"
  },
  {
    "Date": "2025-07-08",
    "Year": "2025",
    "Month": "2025-07",
    "SignUps_Accepted": 0,
    "FirstUploads_Accepted": 0,
    "PaidSubscribers_Accepted": 1,
    "SignUp_Details": "",
    "Upload_Details": "",
    "Paid_Details": "metodocgreal@gmail.com <metodocgreal@gmail.com>",
    "LastUpdated": "2026-06-17 15:40:20"
  },
  {
    "Date": "2025-07-11",
    "Year": "2025",
    "Month": "2025-07",
    "SignUps_Accepted": 0,
    "FirstUploads_Accepted": 0,
    "PaidSubscribers_Accepted": 1,
    "SignUp_Details": "",
    "Upload_Details": "",
    "Paid_Details": "virkley.aquila@gmail.com <virkley.aquila@gmail.com>",
    "LastUpdated": "2026-06-17 15:40:20"
  },
  {
    "Date": "2025-08-06",
    "Year": "2025",
    "Month": "2025-08",
    "SignUps_Accepted": 0,
    "FirstUploads_Accepted": 0,
    "PaidSubscribers_Accepted": 2,
    "SignUp_Details": "",
    "Upload_Details": "",
    "Paid_Details": "ValeriaCabezon <valeriacabezon@diarc.ar>; jon@4kprojects.com <jon@4kprojects.com>",
    "LastUpdated": "2026-06-17 15:40:20"
  },
  {
    "Date": "2025-08-08",
    "Year": "2025",
    "Month": "2025-08",
    "SignUps_Accepted": 0,
    "FirstUploads_Accepted": 0,
    "PaidSubscribers_Accepted": 1,
    "SignUp_Details": "",
    "Upload_Details": "",
    "Paid_Details": "ivan.miskalo@360circuits.com <ivan.miskalo@360circuits.com>",
    "LastUpdated": "2026-06-17 15:40:20"
  },
  {
    "Date": "2025-08-20",
    "Year": "2025",
    "Month": "2025-08",
    "SignUps_Accepted": 0,
    "FirstUploads_Accepted": 0,
    "PaidSubscribers_Accepted": 3,
    "SignUp_Details": "",
    "Upload_Details": "",
    "Paid_Details": "admin@sensoriumxr.com <admin@sensoriumxr.com>; communication.hobold@outlook.com <communication.hobold@outlook.com>; office@thepanoptikon.com <office@thepanoptikon.com>",
    "LastUpdated": "2026-06-17 15:40:20"
  },
  {
    "Date": "2025-08-25",
    "Year": "2025",
    "Month": "2025-08",
    "SignUps_Accepted": 0,
    "FirstUploads_Accepted": 0,
    "PaidSubscribers_Accepted": 1,
    "SignUp_Details": "",
    "Upload_Details": "",
    "Paid_Details": "edumarchi86@gmail.com <edumarchi86@gmail.com>",
    "LastUpdated": "2026-06-17 15:40:20"
  },
  {
    "Date": "2025-08-29",
    "Year": "2025",
    "Month": "2025-08",
    "SignUps_Accepted": 0,
    "FirstUploads_Accepted": 0,
    "PaidSubscribers_Accepted": 1,
    "SignUp_Details": "",
    "Upload_Details": "",
    "Paid_Details": "lAvArtStudio <latif@lavartstudio.com>",
    "LastUpdated": "2026-06-17 15:40:20"
  },
  {
    "Date": "2025-09-02",
    "Year": "2025",
    "Month": "2025-09",
    "SignUps_Accepted": 0,
    "FirstUploads_Accepted": 0,
    "PaidSubscribers_Accepted": 1,
    "SignUp_Details": "",
    "Upload_Details": "",
    "Paid_Details": "pubudu.jayakody@novara.se <pubudu.jayakody@novara.se>",
    "LastUpdated": "2026-06-17 15:40:20"
  },
  {
    "Date": "2025-09-04",
    "Year": "2025",
    "Month": "2025-09",
    "SignUps_Accepted": 0,
    "FirstUploads_Accepted": 0,
    "PaidSubscribers_Accepted": 1,
    "SignUp_Details": "",
    "Upload_Details": "",
    "Paid_Details": "sistema@futura22.com <sistema@futura22.com>",
    "LastUpdated": "2026-06-17 15:40:20"
  },
  {
    "Date": "2025-09-05",
    "Year": "2025",
    "Month": "2025-09",
    "SignUps_Accepted": 0,
    "FirstUploads_Accepted": 0,
    "PaidSubscribers_Accepted": 1,
    "SignUp_Details": "",
    "Upload_Details": "",
    "Paid_Details": "anindasadman <mahmuda65begum@gmail.com>",
    "LastUpdated": "2026-06-17 15:40:20"
  },
  {
    "Date": "2025-09-10",
    "Year": "2025",
    "Month": "2025-09",
    "SignUps_Accepted": 0,
    "FirstUploads_Accepted": 0,
    "PaidSubscribers_Accepted": 1,
    "SignUp_Details": "",
    "Upload_Details": "",
    "Paid_Details": "squall_dandy344@simplelogin.com <squall_dandy344@simplelogin.com>",
    "LastUpdated": "2026-06-17 15:40:20"
  },
  {
    "Date": "2025-09-20",
    "Year": "2025",
    "Month": "2025-09",
    "SignUps_Accepted": 0,
    "FirstUploads_Accepted": 0,
    "PaidSubscribers_Accepted": 1,
    "SignUp_Details": "",
    "Upload_Details": "",
    "Paid_Details": "corp@twin4green.com <corp@twin4green.com>",
    "LastUpdated": "2026-06-17 15:40:20"
  },
  {
    "Date": "2025-09-21",
    "Year": "2025",
    "Month": "2025-09",
    "SignUps_Accepted": 0,
    "FirstUploads_Accepted": 0,
    "PaidSubscribers_Accepted": 1,
    "SignUp_Details": "",
    "Upload_Details": "",
    "Paid_Details": "karim.emad.william@gmail.com <karim.emad.william@gmail.com>",
    "LastUpdated": "2026-06-17 15:40:20"
  },
  {
    "Date": "2025-09-22",
    "Year": "2025",
    "Month": "2025-09",
    "SignUps_Accepted": 0,
    "FirstUploads_Accepted": 0,
    "PaidSubscribers_Accepted": 1,
    "SignUp_Details": "",
    "Upload_Details": "",
    "Paid_Details": "luanhtuankts@gmail.com <luanhtuankts@gmail.com>",
    "LastUpdated": "2026-06-17 15:40:20"
  },
  {
    "Date": "2025-09-24",
    "Year": "2025",
    "Month": "2025-09",
    "SignUps_Accepted": 0,
    "FirstUploads_Accepted": 0,
    "PaidSubscribers_Accepted": 1,
    "SignUp_Details": "",
    "Upload_Details": "",
    "Paid_Details": "Kent512 <nova@novaconceptsny.com>",
    "LastUpdated": "2026-06-17 15:40:20"
  },
  {
    "Date": "2025-09-26",
    "Year": "2025",
    "Month": "2025-09",
    "SignUps_Accepted": 0,
    "FirstUploads_Accepted": 0,
    "PaidSubscribers_Accepted": 2,
    "SignUp_Details": "",
    "Upload_Details": "",
    "Paid_Details": "admin@digitalresidency.com <admin@digitalresidency.com>; rafael@nooked.co <rafael@nooked.co>",
    "LastUpdated": "2026-06-17 15:40:20"
  },
  {
    "Date": "2025-10-02",
    "Year": "2025",
    "Month": "2025-10",
    "SignUps_Accepted": 0,
    "FirstUploads_Accepted": 0,
    "PaidSubscribers_Accepted": 1,
    "SignUp_Details": "",
    "Upload_Details": "",
    "Paid_Details": "tarique.y.mansuri@gmail.com <tarique.y.mansuri@gmail.com>",
    "LastUpdated": "2026-06-17 15:40:20"
  },
  {
    "Date": "2025-10-03",
    "Year": "2025",
    "Month": "2025-10",
    "SignUps_Accepted": 0,
    "FirstUploads_Accepted": 0,
    "PaidSubscribers_Accepted": 1,
    "SignUp_Details": "",
    "Upload_Details": "",
    "Paid_Details": "admin@theinterface.com <admin@theinterface.com>",
    "LastUpdated": "2026-06-17 15:40:20"
  },
  {
    "Date": "2025-10-11",
    "Year": "2025",
    "Month": "2025-10",
    "SignUps_Accepted": 0,
    "FirstUploads_Accepted": 0,
    "PaidSubscribers_Accepted": 1,
    "SignUp_Details": "",
    "Upload_Details": "",
    "Paid_Details": "juanca.arq@gmail.com <juanca.arq@gmail.com>",
    "LastUpdated": "2026-06-17 15:40:20"
  },
  {
    "Date": "2025-10-12",
    "Year": "2025",
    "Month": "2025-10",
    "SignUps_Accepted": 0,
    "FirstUploads_Accepted": 0,
    "PaidSubscribers_Accepted": 1,
    "SignUp_Details": "",
    "Upload_Details": "",
    "Paid_Details": "oliver.b@igo-lean.com <oliver.b@igo-lean.com>",
    "LastUpdated": "2026-06-17 15:40:20"
  },
  {
    "Date": "2025-10-16",
    "Year": "2025",
    "Month": "2025-10",
    "SignUps_Accepted": 0,
    "FirstUploads_Accepted": 0,
    "PaidSubscribers_Accepted": 1,
    "SignUp_Details": "",
    "Upload_Details": "",
    "Paid_Details": "Sambonet Paderno Industrie SpA <media.relations@sambonet.it>",
    "LastUpdated": "2026-06-17 15:40:20"
  },
  {
    "Date": "2025-10-25",
    "Year": "2025",
    "Month": "2025-10",
    "SignUps_Accepted": 0,
    "FirstUploads_Accepted": 0,
    "PaidSubscribers_Accepted": 1,
    "SignUp_Details": "",
    "Upload_Details": "",
    "Paid_Details": "dphakos <daniel.phakos@gmail.com>",
    "LastUpdated": "2026-06-17 15:40:20"
  },
  {
    "Date": "2025-10-28",
    "Year": "2025",
    "Month": "2025-10",
    "SignUps_Accepted": 0,
    "FirstUploads_Accepted": 0,
    "PaidSubscribers_Accepted": 1,
    "SignUp_Details": "",
    "Upload_Details": "",
    "Paid_Details": "Oguz <medlayff@gmail.com>",
    "LastUpdated": "2026-06-17 15:40:20"
  },
  {
    "Date": "2025-10-30",
    "Year": "2025",
    "Month": "2025-10",
    "SignUps_Accepted": 0,
    "FirstUploads_Accepted": 0,
    "PaidSubscribers_Accepted": 1,
    "SignUp_Details": "",
    "Upload_Details": "",
    "Paid_Details": "cotero <cotero@collection-suites.com>",
    "LastUpdated": "2026-06-17 15:40:20"
  },
  {
    "Date": "2025-10-31",
    "Year": "2025",
    "Month": "2025-10",
    "SignUps_Accepted": 0,
    "FirstUploads_Accepted": 0,
    "PaidSubscribers_Accepted": 1,
    "SignUp_Details": "",
    "Upload_Details": "",
    "Paid_Details": "pavelares@gmail.com <pavelares@gmail.com>",
    "LastUpdated": "2026-06-17 15:40:20"
  },
  {
    "Date": "2025-11-07",
    "Year": "2025",
    "Month": "2025-11",
    "SignUps_Accepted": 0,
    "FirstUploads_Accepted": 0,
    "PaidSubscribers_Accepted": 1,
    "SignUp_Details": "",
    "Upload_Details": "",
    "Paid_Details": "info@pieroperilli.com <info@pieroperilli.com>",
    "LastUpdated": "2026-06-17 15:40:20"
  },
  {
    "Date": "2025-11-17",
    "Year": "2025",
    "Month": "2025-11",
    "SignUps_Accepted": 0,
    "FirstUploads_Accepted": 0,
    "PaidSubscribers_Accepted": 1,
    "SignUp_Details": "",
    "Upload_Details": "",
    "Paid_Details": "elunitycare@gmail.com <elunitycare@gmail.com>",
    "LastUpdated": "2026-06-17 15:40:20"
  },
  {
    "Date": "2025-11-18",
    "Year": "2025",
    "Month": "2025-11",
    "SignUps_Accepted": 0,
    "FirstUploads_Accepted": 0,
    "PaidSubscribers_Accepted": 1,
    "SignUp_Details": "",
    "Upload_Details": "",
    "Paid_Details": "john@olsonyachtgroup.com <john@olsonyachtgroup.com>",
    "LastUpdated": "2026-06-17 15:40:20"
  },
  {
    "Date": "2025-11-19",
    "Year": "2025",
    "Month": "2025-11",
    "SignUps_Accepted": 0,
    "FirstUploads_Accepted": 0,
    "PaidSubscribers_Accepted": 1,
    "SignUp_Details": "",
    "Upload_Details": "",
    "Paid_Details": "iamxlive@gmail.com <iamxlive@gmail.com>",
    "LastUpdated": "2026-06-17 15:40:20"
  },
  {
    "Date": "2025-12-01",
    "Year": "2025",
    "Month": "2025-12",
    "SignUps_Accepted": 0,
    "FirstUploads_Accepted": 0,
    "PaidSubscribers_Accepted": 1,
    "SignUp_Details": "",
    "Upload_Details": "",
    "Paid_Details": "OneOfApes <alex1petrash@gmail.com>",
    "LastUpdated": "2026-06-17 15:40:20"
  },
  {
    "Date": "2025-12-03",
    "Year": "2025",
    "Month": "2025-12",
    "SignUps_Accepted": 0,
    "FirstUploads_Accepted": 1,
    "PaidSubscribers_Accepted": 0,
    "SignUp_Details": "",
    "Upload_Details": "esrever <john@olsonyachtgroup.com>",
    "Paid_Details": "",
    "LastUpdated": "2026-06-17 15:40:20"
  },
  {
    "Date": "2025-12-04",
    "Year": "2025",
    "Month": "2025-12",
    "SignUps_Accepted": 0,
    "FirstUploads_Accepted": 1,
    "PaidSubscribers_Accepted": 0,
    "SignUp_Details": "",
    "Upload_Details": "abdalla94 <abdalla_alaied@yahoo.com>",
    "Paid_Details": "",
    "LastUpdated": "2026-06-17 15:40:20"
  },
  {
    "Date": "2025-12-05",
    "Year": "2025",
    "Month": "2025-12",
    "SignUps_Accepted": 0,
    "FirstUploads_Accepted": 1,
    "PaidSubscribers_Accepted": 0,
    "SignUp_Details": "",
    "Upload_Details": "jackylam <s02032a15@gmail.com>",
    "Paid_Details": "",
    "LastUpdated": "2026-06-17 15:40:20"
  },
  {
    "Date": "2025-12-10",
    "Year": "2025",
    "Month": "2025-12",
    "SignUps_Accepted": 0,
    "FirstUploads_Accepted": 0,
    "PaidSubscribers_Accepted": 1,
    "SignUp_Details": "",
    "Upload_Details": "",
    "Paid_Details": "Tkhlashidze <tkhlashidzerati@gmail.com>",
    "LastUpdated": "2026-06-17 15:40:20"
  },
  {
    "Date": "2025-12-14",
    "Year": "2025",
    "Month": "2025-12",
    "SignUps_Accepted": 0,
    "FirstUploads_Accepted": 1,
    "PaidSubscribers_Accepted": 0,
    "SignUp_Details": "",
    "Upload_Details": "OneOfApes <alex1petrash@gmail.com>",
    "Paid_Details": "",
    "LastUpdated": "2026-06-17 15:40:20"
  },
  {
    "Date": "2025-12-17",
    "Year": "2025",
    "Month": "2025-12",
    "SignUps_Accepted": 0,
    "FirstUploads_Accepted": 0,
    "PaidSubscribers_Accepted": 1,
    "SignUp_Details": "",
    "Upload_Details": "",
    "Paid_Details": "walhargohar@gmail.com <walhargohar@gmail.com>",
    "LastUpdated": "2026-06-17 15:40:20"
  },
  {
    "Date": "2025-12-19",
    "Year": "2025",
    "Month": "2025-12",
    "SignUps_Accepted": 0,
    "FirstUploads_Accepted": 1,
    "PaidSubscribers_Accepted": 0,
    "SignUp_Details": "",
    "Upload_Details": "Agcaonr <agcaonr@gmail.com>",
    "Paid_Details": "",
    "LastUpdated": "2026-06-17 15:40:20"
  },
  {
    "Date": "2025-12-20",
    "Year": "2025",
    "Month": "2025-12",
    "SignUps_Accepted": 0,
    "FirstUploads_Accepted": 1,
    "PaidSubscribers_Accepted": 0,
    "SignUp_Details": "",
    "Upload_Details": "Testing <hosali1255@gmail.com>",
    "Paid_Details": "",
    "LastUpdated": "2026-06-17 15:40:20"
  },
  {
    "Date": "2025-12-21",
    "Year": "2025",
    "Month": "2025-12",
    "SignUps_Accepted": 0,
    "FirstUploads_Accepted": 0,
    "PaidSubscribers_Accepted": 1,
    "SignUp_Details": "",
    "Upload_Details": "",
    "Paid_Details": "faraipiloto@aol.com <faraipiloto@aol.com>",
    "LastUpdated": "2026-06-17 15:40:20"
  },
  {
    "Date": "2025-12-22",
    "Year": "2025",
    "Month": "2025-12",
    "SignUps_Accepted": 0,
    "FirstUploads_Accepted": 1,
    "PaidSubscribers_Accepted": 0,
    "SignUp_Details": "",
    "Upload_Details": "Hemil_Ganatra <hemil.ganatra@gmail.com>",
    "Paid_Details": "",
    "LastUpdated": "2026-06-17 15:40:20"
  },
  {
    "Date": "2025-12-24",
    "Year": "2025",
    "Month": "2025-12",
    "SignUps_Accepted": 0,
    "FirstUploads_Accepted": 0,
    "PaidSubscribers_Accepted": 1,
    "SignUp_Details": "",
    "Upload_Details": "",
    "Paid_Details": "lecorrebenoit33@gmail.com <lecorrebenoit33@gmail.com>",
    "LastUpdated": "2026-06-17 15:40:20"
  },
  {
    "Date": "2025-12-27",
    "Year": "2025",
    "Month": "2025-12",
    "SignUps_Accepted": 0,
    "FirstUploads_Accepted": 0,
    "PaidSubscribers_Accepted": 1,
    "SignUp_Details": "",
    "Upload_Details": "",
    "Paid_Details": "Akshita <akshitapatni27@gmail.com>",
    "LastUpdated": "2026-06-17 15:40:20"
  },
  {
    "Date": "2026-01-02",
    "Year": "2026",
    "Month": "2026-01",
    "SignUps_Accepted": 0,
    "FirstUploads_Accepted": 0,
    "PaidSubscribers_Accepted": 1,
    "SignUp_Details": "",
    "Upload_Details": "",
    "Paid_Details": "ianokinda <ianokinda@gmail.com>",
    "LastUpdated": "2026-06-17 15:40:20"
  },
  {
    "Date": "2026-01-09",
    "Year": "2026",
    "Month": "2026-01",
    "SignUps_Accepted": 0,
    "FirstUploads_Accepted": 0,
    "PaidSubscribers_Accepted": 1,
    "SignUp_Details": "",
    "Upload_Details": "",
    "Paid_Details": "haukur@perlan.is <haukur@perlan.is>",
    "LastUpdated": "2026-06-17 15:40:20"
  },
  {
    "Date": "2026-01-15",
    "Year": "2026",
    "Month": "2026-01",
    "SignUps_Accepted": 0,
    "FirstUploads_Accepted": 0,
    "PaidSubscribers_Accepted": 1,
    "SignUp_Details": "",
    "Upload_Details": "",
    "Paid_Details": "lindiwe.morrison@smiths.com <lindiwe.morrison@smiths.com>",
    "LastUpdated": "2026-06-17 15:40:20"
  },
  {
    "Date": "2026-01-18",
    "Year": "2026",
    "Month": "2026-01",
    "SignUps_Accepted": 0,
    "FirstUploads_Accepted": 0,
    "PaidSubscribers_Accepted": 1,
    "SignUp_Details": "",
    "Upload_Details": "",
    "Paid_Details": "daniele.frontini@motik.it <daniele.frontini@motik.it>",
    "LastUpdated": "2026-06-17 15:40:20"
  },
  {
    "Date": "2026-01-19",
    "Year": "2026",
    "Month": "2026-01",
    "SignUps_Accepted": 0,
    "FirstUploads_Accepted": 0,
    "PaidSubscribers_Accepted": 1,
    "SignUp_Details": "",
    "Upload_Details": "",
    "Paid_Details": "team@mappings.ai <team@mappings.ai>",
    "LastUpdated": "2026-06-17 15:40:20"
  },
  {
    "Date": "2026-01-26",
    "Year": "2026",
    "Month": "2026-01",
    "SignUps_Accepted": 0,
    "FirstUploads_Accepted": 2,
    "PaidSubscribers_Accepted": 1,
    "SignUp_Details": "",
    "Upload_Details": "JulianSong1990 <julian.song@homeperception.com>; Veith <nurtsch.veith@googlemail.com>",
    "Paid_Details": "vrvmarine@gmail.com <vrvmarine@gmail.com>",
    "LastUpdated": "2026-06-17 15:40:20"
  },
  {
    "Date": "2026-01-27",
    "Year": "2026",
    "Month": "2026-01",
    "SignUps_Accepted": 0,
    "FirstUploads_Accepted": 0,
    "PaidSubscribers_Accepted": 1,
    "SignUp_Details": "",
    "Upload_Details": "",
    "Paid_Details": "nwitsupport@hdrinc.com <nwitsupport@hdrinc.com>",
    "LastUpdated": "2026-06-17 15:40:20"
  },
  {
    "Date": "2026-01-31",
    "Year": "2026",
    "Month": "2026-01",
    "SignUps_Accepted": 0,
    "FirstUploads_Accepted": 2,
    "PaidSubscribers_Accepted": 0,
    "SignUp_Details": "",
    "Upload_Details": "154vfxs <luizaclara.saga@gmail.com>; CarollCher <maycaroll182@gmail.com>",
    "Paid_Details": "",
    "LastUpdated": "2026-06-17 15:40:20"
  },
  {
    "Date": "2026-02-02",
    "Year": "2026",
    "Month": "2026-02",
    "SignUps_Accepted": 0,
    "FirstUploads_Accepted": 0,
    "PaidSubscribers_Accepted": 1,
    "SignUp_Details": "",
    "Upload_Details": "",
    "Paid_Details": "accounting@kauel.ai <accounting@kauel.ai>",
    "LastUpdated": "2026-06-17 15:40:20"
  },
  {
    "Date": "2026-02-05",
    "Year": "2026",
    "Month": "2026-02",
    "SignUps_Accepted": 0,
    "FirstUploads_Accepted": 2,
    "PaidSubscribers_Accepted": 0,
    "SignUp_Details": "",
    "Upload_Details": "James_TNR <james.evans@truenorthrail.com>; JanRucil <rucil.jan@gmail.com>",
    "Paid_Details": "",
    "LastUpdated": "2026-06-17 15:40:20"
  },
  {
    "Date": "2026-02-06",
    "Year": "2026",
    "Month": "2026-02",
    "SignUps_Accepted": 0,
    "FirstUploads_Accepted": 0,
    "PaidSubscribers_Accepted": 1,
    "SignUp_Details": "",
    "Upload_Details": "",
    "Paid_Details": "design@exhibithappy.com <design@exhibithappy.com>",
    "LastUpdated": "2026-06-17 15:40:20"
  },
  {
    "Date": "2026-02-09",
    "Year": "2026",
    "Month": "2026-02",
    "SignUps_Accepted": 0,
    "FirstUploads_Accepted": 3,
    "PaidSubscribers_Accepted": 1,
    "SignUp_Details": "",
    "Upload_Details": "MileleMuseum <info@milele.space>; ianokinda <ianokinda@gmail.com>; tanzibul <tanzib31@gmail.com>",
    "Paid_Details": "malpaniconfig@gmail.com <malpaniconfig@gmail.com>",
    "LastUpdated": "2026-06-17 15:40:20"
  },
  {
    "Date": "2026-02-10",
    "Year": "2026",
    "Month": "2026-02",
    "SignUps_Accepted": 0,
    "FirstUploads_Accepted": 3,
    "PaidSubscribers_Accepted": 1,
    "SignUp_Details": "",
    "Upload_Details": "E3DS_SA <sabbirahmed.eee16@gmail.com>; E3DS_SCD <srijonbdcom@gmail.com>; E3DS_rafshan <sabbirshovon96@gmail.com>",
    "Paid_Details": "neuroarchitex@gmail.com <neuroarchitex@gmail.com>",
    "LastUpdated": "2026-06-17 15:40:20"
  },
  {
    "Date": "2026-02-11",
    "Year": "2026",
    "Month": "2026-02",
    "SignUps_Accepted": 0,
    "FirstUploads_Accepted": 1,
    "PaidSubscribers_Accepted": 0,
    "SignUp_Details": "",
    "Upload_Details": "SpaceForm <it@spaceform.io>",
    "Paid_Details": "",
    "LastUpdated": "2026-06-17 15:40:20"
  },
  {
    "Date": "2026-02-12",
    "Year": "2026",
    "Month": "2026-02",
    "SignUps_Accepted": 0,
    "FirstUploads_Accepted": 1,
    "PaidSubscribers_Accepted": 0,
    "SignUp_Details": "",
    "Upload_Details": "Rob_FKDStudio <rob@fkdstudio.com.au>",
    "Paid_Details": "",
    "LastUpdated": "2026-06-17 15:40:20"
  },
  {
    "Date": "2026-02-13",
    "Year": "2026",
    "Month": "2026-02",
    "SignUps_Accepted": 0,
    "FirstUploads_Accepted": 1,
    "PaidSubscribers_Accepted": 0,
    "SignUp_Details": "",
    "Upload_Details": "TitaniumAG <luke.jeffers41@gmail.com>",
    "Paid_Details": "",
    "LastUpdated": "2026-06-17 15:40:20"
  },
  {
    "Date": "2026-02-16",
    "Year": "2026",
    "Month": "2026-02",
    "SignUps_Accepted": 0,
    "FirstUploads_Accepted": 1,
    "PaidSubscribers_Accepted": 0,
    "SignUp_Details": "",
    "Upload_Details": "jerruco <jerruco@gmail.com>",
    "Paid_Details": "",
    "LastUpdated": "2026-06-17 15:40:20"
  },
  {
    "Date": "2026-02-17",
    "Year": "2026",
    "Month": "2026-02",
    "SignUps_Accepted": 0,
    "FirstUploads_Accepted": 0,
    "PaidSubscribers_Accepted": 1,
    "SignUp_Details": "",
    "Upload_Details": "",
    "Paid_Details": "rob@fkdstudio.com.au <rob@fkdstudio.com.au>",
    "LastUpdated": "2026-06-17 15:40:20"
  },
  {
    "Date": "2026-02-18",
    "Year": "2026",
    "Month": "2026-02",
    "SignUps_Accepted": 0,
    "FirstUploads_Accepted": 3,
    "PaidSubscribers_Accepted": 0,
    "SignUp_Details": "",
    "Upload_Details": "Cory <cory.motion.exe@gmail.com>; Lucas <lucas@valurai.com>; kmlmndc <kemalmandaci@gmail.com>",
    "Paid_Details": "",
    "LastUpdated": "2026-06-17 15:40:20"
  },
  {
    "Date": "2026-02-19",
    "Year": "2026",
    "Month": "2026-02",
    "SignUps_Accepted": 0,
    "FirstUploads_Accepted": 1,
    "PaidSubscribers_Accepted": 1,
    "SignUp_Details": "",
    "Upload_Details": "jhonno117 <slsamgv12@gmail.com>",
    "Paid_Details": "contact@robindeclercq.com <contact@robindeclercq.com>",
    "LastUpdated": "2026-06-17 15:40:20"
  },
  {
    "Date": "2026-02-20",
    "Year": "2026",
    "Month": "2026-02",
    "SignUps_Accepted": 0,
    "FirstUploads_Accepted": 1,
    "PaidSubscribers_Accepted": 0,
    "SignUp_Details": "",
    "Upload_Details": "MinTest <minhodong9@gmail.com>",
    "Paid_Details": "",
    "LastUpdated": "2026-06-17 15:40:20"
  },
  {
    "Date": "2026-02-23",
    "Year": "2026",
    "Month": "2026-02",
    "SignUps_Accepted": 0,
    "FirstUploads_Accepted": 3,
    "PaidSubscribers_Accepted": 1,
    "SignUp_Details": "",
    "Upload_Details": "Usharjeel10 <usamasharjeel0@gmail.com>; alex <alzosmol@mail.ru>; ttbil123 <ttbilgili40@hotmail.com>",
    "Paid_Details": "minhodong9@gmail.com <minhodong9@gmail.com>",
    "LastUpdated": "2026-06-17 15:40:20"
  },
  {
    "Date": "2026-02-24",
    "Year": "2026",
    "Month": "2026-02",
    "SignUps_Accepted": 0,
    "FirstUploads_Accepted": 3,
    "PaidSubscribers_Accepted": 0,
    "SignUp_Details": "",
    "Upload_Details": "AAVISHKARbySAMAY <ofc.samay@gmail.com>; Amjad <amjadkhater95@gmail.com>; pixelstreaming <pixelstreaming173@gmail.com>",
    "Paid_Details": "",
    "LastUpdated": "2026-06-17 15:40:20"
  },
  {
    "Date": "2026-02-25",
    "Year": "2026",
    "Month": "2026-02",
    "SignUps_Accepted": 0,
    "FirstUploads_Accepted": 0,
    "PaidSubscribers_Accepted": 1,
    "SignUp_Details": "",
    "Upload_Details": "",
    "Paid_Details": "rezidenciarurky@gmail.com <rezidenciarurky@gmail.com>",
    "LastUpdated": "2026-06-17 15:40:20"
  },
  {
    "Date": "2026-02-26",
    "Year": "2026",
    "Month": "2026-02",
    "SignUps_Accepted": 0,
    "FirstUploads_Accepted": 2,
    "PaidSubscribers_Accepted": 1,
    "SignUp_Details": "",
    "Upload_Details": "Artavazd <papikyan.artavazd1@gmail.com>; ttbil <ttbilgili40@gmail.com>",
    "Paid_Details": "emanueleoriglia@kimera-automobili.com <emanueleoriglia@kimera-automobili.com>",
    "LastUpdated": "2026-06-17 15:40:20"
  },
  {
    "Date": "2026-02-27",
    "Year": "2026",
    "Month": "2026-02",
    "SignUps_Accepted": 0,
    "FirstUploads_Accepted": 0,
    "PaidSubscribers_Accepted": 1,
    "SignUp_Details": "",
    "Upload_Details": "",
    "Paid_Details": "steven@fullbarsmedia.com <steven@fullbarsmedia.com>",
    "LastUpdated": "2026-06-17 15:40:20"
  },
  {
    "Date": "2026-02-28",
    "Year": "2026",
    "Month": "2026-02",
    "SignUps_Accepted": 0,
    "FirstUploads_Accepted": 2,
    "PaidSubscribers_Accepted": 0,
    "SignUp_Details": "",
    "Upload_Details": "Dagarre <dagarre00@gmail.com>; rv360 <mercadeoporlaweb@gmail.com>",
    "Paid_Details": "",
    "LastUpdated": "2026-06-17 15:40:20"
  },
  {
    "Date": "2026-03-01",
    "Year": "2026",
    "Month": "2026-03",
    "SignUps_Accepted": 0,
    "FirstUploads_Accepted": 1,
    "PaidSubscribers_Accepted": 0,
    "SignUp_Details": "",
    "Upload_Details": "nexustwin <morgan@twinnation.co.uk>",
    "Paid_Details": "",
    "LastUpdated": "2026-06-17 15:40:20"
  },
  {
    "Date": "2026-03-05",
    "Year": "2026",
    "Month": "2026-03",
    "SignUps_Accepted": 0,
    "FirstUploads_Accepted": 2,
    "PaidSubscribers_Accepted": 0,
    "SignUp_Details": "",
    "Upload_Details": "Jerruco <jerruco@hotmail.com>; kathyu.168 <kathleen.yu@nudgyt.com>",
    "Paid_Details": "",
    "LastUpdated": "2026-06-17 15:40:20"
  },
  {
    "Date": "2026-03-09",
    "Year": "2026",
    "Month": "2026-03",
    "SignUps_Accepted": 0,
    "FirstUploads_Accepted": 1,
    "PaidSubscribers_Accepted": 0,
    "SignUp_Details": "",
    "Upload_Details": "chateauz <explore@chateauz.io>",
    "Paid_Details": "",
    "LastUpdated": "2026-06-17 15:40:20"
  },
  {
    "Date": "2026-03-10",
    "Year": "2026",
    "Month": "2026-03",
    "SignUps_Accepted": 0,
    "FirstUploads_Accepted": 0,
    "PaidSubscribers_Accepted": 1,
    "SignUp_Details": "",
    "Upload_Details": "",
    "Paid_Details": "libelium <aj.jara@libelium.com>",
    "LastUpdated": "2026-06-17 15:40:20"
  },
  {
    "Date": "2026-03-12",
    "Year": "2026",
    "Month": "2026-03",
    "SignUps_Accepted": 0,
    "FirstUploads_Accepted": 0,
    "PaidSubscribers_Accepted": 1,
    "SignUp_Details": "",
    "Upload_Details": "",
    "Paid_Details": "smartspatial <arthur@smartspatial.com>",
    "LastUpdated": "2026-06-17 15:40:20"
  },
  {
    "Date": "2026-03-14",
    "Year": "2026",
    "Month": "2026-03",
    "SignUps_Accepted": 0,
    "FirstUploads_Accepted": 0,
    "PaidSubscribers_Accepted": 1,
    "SignUp_Details": "",
    "Upload_Details": "",
    "Paid_Details": "Ivan_01 <crazzytapir@gmail.com>",
    "LastUpdated": "2026-06-17 15:40:20"
  },
  {
    "Date": "2026-03-16",
    "Year": "2026",
    "Month": "2026-03",
    "SignUps_Accepted": 0,
    "FirstUploads_Accepted": 2,
    "PaidSubscribers_Accepted": 0,
    "SignUp_Details": "",
    "Upload_Details": "lanterne_digitale <info@lanternedigitale.com>; steved <steve@rupture.mt>",
    "Paid_Details": "",
    "LastUpdated": "2026-06-17 15:40:20"
  },
  {
    "Date": "2026-03-17",
    "Year": "2026",
    "Month": "2026-03",
    "SignUps_Accepted": 0,
    "FirstUploads_Accepted": 0,
    "PaidSubscribers_Accepted": 1,
    "SignUp_Details": "",
    "Upload_Details": "",
    "Paid_Details": "Totsan <totsandesign@gmail.com>",
    "LastUpdated": "2026-06-17 15:40:20"
  },
  {
    "Date": "2026-03-18",
    "Year": "2026",
    "Month": "2026-03",
    "SignUps_Accepted": 0,
    "FirstUploads_Accepted": 1,
    "PaidSubscribers_Accepted": 0,
    "SignUp_Details": "",
    "Upload_Details": "Menakta <menakta@gmail.com>",
    "Paid_Details": "",
    "LastUpdated": "2026-06-17 15:40:20"
  },
  {
    "Date": "2026-03-19",
    "Year": "2026",
    "Month": "2026-03",
    "SignUps_Accepted": 0,
    "FirstUploads_Accepted": 0,
    "PaidSubscribers_Accepted": 1,
    "SignUp_Details": "",
    "Upload_Details": "",
    "Paid_Details": "it@lunas.pro <it@lunas.pro>",
    "LastUpdated": "2026-06-17 15:40:20"
  },
  {
    "Date": "2026-03-21",
    "Year": "2026",
    "Month": "2026-03",
    "SignUps_Accepted": 0,
    "FirstUploads_Accepted": 1,
    "PaidSubscribers_Accepted": 0,
    "SignUp_Details": "",
    "Upload_Details": "futureact <info@futureact.eu>",
    "Paid_Details": "",
    "LastUpdated": "2026-06-17 15:40:20"
  },
  {
    "Date": "2026-03-24",
    "Year": "2026",
    "Month": "2026-03",
    "SignUps_Accepted": 0,
    "FirstUploads_Accepted": 0,
    "PaidSubscribers_Accepted": 1,
    "SignUp_Details": "",
    "Upload_Details": "",
    "Paid_Details": "Amanoo <khakhamyanh@gmail.com>",
    "LastUpdated": "2026-06-17 15:40:20"
  },
  {
    "Date": "2026-03-26",
    "Year": "2026",
    "Month": "2026-03",
    "SignUps_Accepted": 0,
    "FirstUploads_Accepted": 1,
    "PaidSubscribers_Accepted": 0,
    "SignUp_Details": "",
    "Upload_Details": "Debanjan2 <debanjan798094@gmail.com>",
    "Paid_Details": "",
    "LastUpdated": "2026-06-17 15:40:20"
  },
  {
    "Date": "2026-03-27",
    "Year": "2026",
    "Month": "2026-03",
    "SignUps_Accepted": 0,
    "FirstUploads_Accepted": 1,
    "PaidSubscribers_Accepted": 0,
    "SignUp_Details": "",
    "Upload_Details": "ryanhayle <ryan.hayle@open.ac.uk>",
    "Paid_Details": "",
    "LastUpdated": "2026-06-17 15:40:20"
  },
  {
    "Date": "2026-03-28",
    "Year": "2026",
    "Month": "2026-03",
    "SignUps_Accepted": 0,
    "FirstUploads_Accepted": 2,
    "PaidSubscribers_Accepted": 1,
    "SignUp_Details": "",
    "Upload_Details": "JustinMRedd <justin.michael.redd@gmail.com>; KurtWeaver <kurtisweaver@boilerplatestudios.com>",
    "Paid_Details": "KurtWeaver <kurtisweaver@boilerplatestudios.com>",
    "LastUpdated": "2026-06-17 15:40:20"
  },
  {
    "Date": "2026-03-31",
    "Year": "2026",
    "Month": "2026-03",
    "SignUps_Accepted": 0,
    "FirstUploads_Accepted": 1,
    "PaidSubscribers_Accepted": 0,
    "SignUp_Details": "",
    "Upload_Details": "Miras <mirasgt152@gmail.com>",
    "Paid_Details": "",
    "LastUpdated": "2026-06-17 15:40:20"
  },
  {
    "Date": "2026-04-01",
    "Year": "2026",
    "Month": "2026-04",
    "SignUps_Accepted": 0,
    "FirstUploads_Accepted": 0,
    "PaidSubscribers_Accepted": 1,
    "SignUp_Details": "",
    "Upload_Details": "",
    "Paid_Details": "WSP_VisualStudios <carrie.loyd@wsp.com>",
    "LastUpdated": "2026-06-17 15:40:20"
  },
  {
    "Date": "2026-04-03",
    "Year": "2026",
    "Month": "2026-04",
    "SignUps_Accepted": 0,
    "FirstUploads_Accepted": 0,
    "PaidSubscribers_Accepted": 1,
    "SignUp_Details": "",
    "Upload_Details": "",
    "Paid_Details": "yugich <yugich2@gmail.com>",
    "LastUpdated": "2026-06-17 15:40:20"
  },
  {
    "Date": "2026-04-08",
    "Year": "2026",
    "Month": "2026-04",
    "SignUps_Accepted": 0,
    "FirstUploads_Accepted": 1,
    "PaidSubscribers_Accepted": 0,
    "SignUp_Details": "",
    "Upload_Details": "harsh_s <hvshete6@gmail.com>",
    "Paid_Details": "",
    "LastUpdated": "2026-06-17 15:40:20"
  },
  {
    "Date": "2026-04-09",
    "Year": "2026",
    "Month": "2026-04",
    "SignUps_Accepted": 0,
    "FirstUploads_Accepted": 1,
    "PaidSubscribers_Accepted": 0,
    "SignUp_Details": "",
    "Upload_Details": "3DHome4U <liubomirmarinkov@gmail.com>",
    "Paid_Details": "",
    "LastUpdated": "2026-06-17 15:40:20"
  },
  {
    "Date": "2026-04-10",
    "Year": "2026",
    "Month": "2026-04",
    "SignUps_Accepted": 0,
    "FirstUploads_Accepted": 2,
    "PaidSubscribers_Accepted": 2,
    "SignUp_Details": "",
    "Upload_Details": "ArchPic <timd@archpic.com>; MWX_Deploy <fathema@metaworldx.com>",
    "Paid_Details": "Adapt3D <isak@adapt.se>; aicollision <david.elder85@gmail.com>",
    "LastUpdated": "2026-06-17 15:40:20"
  },
  {
    "Date": "2026-04-13",
    "Year": "2026",
    "Month": "2026-04",
    "SignUps_Accepted": 0,
    "FirstUploads_Accepted": 0,
    "PaidSubscribers_Accepted": 2,
    "SignUp_Details": "",
    "Upload_Details": "",
    "Paid_Details": "Stephane Ely <stephane@elycorp.com>; Tedson <boris.turkic@tedsonmotors.com>",
    "LastUpdated": "2026-06-17 15:40:20"
  },
  {
    "Date": "2026-04-14",
    "Year": "2026",
    "Month": "2026-04",
    "SignUps_Accepted": 0,
    "FirstUploads_Accepted": 0,
    "PaidSubscribers_Accepted": 2,
    "SignUp_Details": "",
    "Upload_Details": "",
    "Paid_Details": "Domure <info@retech.life>; benunsworth <ben.unsworth@lumeto.com>",
    "LastUpdated": "2026-06-17 15:40:20"
  },
  {
    "Date": "2026-04-15",
    "Year": "2026",
    "Month": "2026-04",
    "SignUps_Accepted": 0,
    "FirstUploads_Accepted": 0,
    "PaidSubscribers_Accepted": 1,
    "SignUp_Details": "",
    "Upload_Details": "",
    "Paid_Details": "BossHomes <harouto@me.com>",
    "LastUpdated": "2026-06-17 15:40:20"
  },
  {
    "Date": "2026-04-16",
    "Year": "2026",
    "Month": "2026-04",
    "SignUps_Accepted": 0,
    "FirstUploads_Accepted": 0,
    "PaidSubscribers_Accepted": 2,
    "SignUp_Details": "",
    "Upload_Details": "",
    "Paid_Details": "DomWorld <domworldhub@gmail.com>; H3re <info@h3re.it>",
    "LastUpdated": "2026-06-17 15:40:20"
  },
  {
    "Date": "2026-04-17",
    "Year": "2026",
    "Month": "2026-04",
    "SignUps_Accepted": 0,
    "FirstUploads_Accepted": 0,
    "PaidSubscribers_Accepted": 1,
    "SignUp_Details": "",
    "Upload_Details": "",
    "Paid_Details": "Elijahbonds <elijahbonds1@gmail.com>",
    "LastUpdated": "2026-06-17 15:40:20"
  },
  {
    "Date": "2026-04-21",
    "Year": "2026",
    "Month": "2026-04",
    "SignUps_Accepted": 0,
    "FirstUploads_Accepted": 0,
    "PaidSubscribers_Accepted": 1,
    "SignUp_Details": "",
    "Upload_Details": "",
    "Paid_Details": "gamestrixstudio <gamestrixstudios@gmail.com>",
    "LastUpdated": "2026-06-17 15:40:20"
  },
  {
    "Date": "2026-04-23",
    "Year": "2026",
    "Month": "2026-04",
    "SignUps_Accepted": 0,
    "FirstUploads_Accepted": 0,
    "PaidSubscribers_Accepted": 1,
    "SignUp_Details": "",
    "Upload_Details": "",
    "Paid_Details": "mrupp <info@manuelrupp.com>",
    "LastUpdated": "2026-06-17 15:40:20"
  },
  {
    "Date": "2026-04-27",
    "Year": "2026",
    "Month": "2026-04",
    "SignUps_Accepted": 0,
    "FirstUploads_Accepted": 0,
    "PaidSubscribers_Accepted": 1,
    "SignUp_Details": "",
    "Upload_Details": "",
    "Paid_Details": "EleganzaAdmin <it@eleganza.ai>",
    "LastUpdated": "2026-06-17 15:40:20"
  },
  {
    "Date": "2026-04-29",
    "Year": "2026",
    "Month": "2026-04",
    "SignUps_Accepted": 0,
    "FirstUploads_Accepted": 1,
    "PaidSubscribers_Accepted": 0,
    "SignUp_Details": "",
    "Upload_Details": "StudioDizajnPetica <fashioninmotion88@gmail.com>",
    "Paid_Details": "",
    "LastUpdated": "2026-06-17 15:40:20"
  },
  {
    "Date": "2026-05-03",
    "Year": "2026",
    "Month": "2026-05",
    "SignUps_Accepted": 0,
    "FirstUploads_Accepted": 0,
    "PaidSubscribers_Accepted": 1,
    "SignUp_Details": "",
    "Upload_Details": "",
    "Paid_Details": "InteractiVR <achilds@reflectionsproduction.com>",
    "LastUpdated": "2026-06-17 15:40:20"
  },
  {
    "Date": "2026-05-04",
    "Year": "2026",
    "Month": "2026-05",
    "SignUps_Accepted": 0,
    "FirstUploads_Accepted": 0,
    "PaidSubscribers_Accepted": 1,
    "SignUp_Details": "",
    "Upload_Details": "",
    "Paid_Details": "ALTUNYAPI <koksalcakici@hotmail.com>",
    "LastUpdated": "2026-06-17 15:40:20"
  },
  {
    "Date": "2026-05-05",
    "Year": "2026",
    "Month": "2026-05",
    "SignUps_Accepted": 0,
    "FirstUploads_Accepted": 1,
    "PaidSubscribers_Accepted": 0,
    "SignUp_Details": "",
    "Upload_Details": "elyprod <stephane@elycorp.com>",
    "Paid_Details": "",
    "LastUpdated": "2026-06-17 15:40:20"
  },
  {
    "Date": "2026-05-06",
    "Year": "2026",
    "Month": "2026-05",
    "SignUps_Accepted": 0,
    "FirstUploads_Accepted": 0,
    "PaidSubscribers_Accepted": 2,
    "SignUp_Details": "",
    "Upload_Details": "",
    "Paid_Details": "Aaron Kocurek <aaron@enhancedimage.com>; bmo <brianmorris6693@gmail.com>",
    "LastUpdated": "2026-06-17 15:40:20"
  },
  {
    "Date": "2026-05-07",
    "Year": "2026",
    "Month": "2026-05",
    "SignUps_Accepted": 0,
    "FirstUploads_Accepted": 3,
    "PaidSubscribers_Accepted": 2,
    "SignUp_Details": "",
    "Upload_Details": "ALTUNYAPI <koksalcakici@hotmail.com>; Shantideep <dipakshantideep@gmail.com>; glitch <glisic.goran1@gmail.com>",
    "Paid_Details": "Shantideep <dipakshantideep@gmail.com>; libelium3d <jara@libelium.com>",
    "LastUpdated": "2026-06-17 15:40:20"
  },
  {
    "Date": "2026-05-09",
    "Year": "2026",
    "Month": "2026-05",
    "SignUps_Accepted": 0,
    "FirstUploads_Accepted": 2,
    "PaidSubscribers_Accepted": 1,
    "SignUp_Details": "",
    "Upload_Details": "FORCE <blackholeinfiverse29@gmail.com>; Nazibul_Alam <exposefurniture.marketing@gmail.com>",
    "Paid_Details": "Amjad_Fielat <amjad.kamel94@gmail.com>",
    "LastUpdated": "2026-06-17 15:40:20"
  },
  {
    "Date": "2026-05-11",
    "Year": "2026",
    "Month": "2026-05",
    "SignUps_Accepted": 0,
    "FirstUploads_Accepted": 2,
    "PaidSubscribers_Accepted": 0,
    "SignUp_Details": "",
    "Upload_Details": "askSIM <marufsim95@gmail.com>; cmyers27 <djcm16@gmail.com>",
    "Paid_Details": "",
    "LastUpdated": "2026-06-17 15:40:20"
  },
  {
    "Date": "2026-05-12",
    "Year": "2026",
    "Month": "2026-05",
    "SignUps_Accepted": 0,
    "FirstUploads_Accepted": 2,
    "PaidSubscribers_Accepted": 0,
    "SignUp_Details": "",
    "Upload_Details": "Ivansilum <ivansilum@gmail.com>; Mansoor7 <muhammad.mansoor@mim.archi>",
    "Paid_Details": "",
    "LastUpdated": "2026-06-17 15:40:20"
  },
  {
    "Date": "2026-05-13",
    "Year": "2026",
    "Month": "2026-05",
    "SignUps_Accepted": 0,
    "FirstUploads_Accepted": 1,
    "PaidSubscribers_Accepted": 2,
    "SignUp_Details": "",
    "Upload_Details": "Nrperzent <masterpvz95@gmail.com>",
    "Paid_Details": "sdestro <s.destro@dils.com>; snakandala <sara@johannamolineus.com>",
    "LastUpdated": "2026-06-17 15:40:20"
  },
  {
    "Date": "2026-05-14",
    "Year": "2026",
    "Month": "2026-05",
    "SignUps_Accepted": 0,
    "FirstUploads_Accepted": 2,
    "PaidSubscribers_Accepted": 0,
    "SignUp_Details": "",
    "Upload_Details": "Pavlo <pavelsplavel@gmail.com>; libelium3d <jara@libelium.com>",
    "Paid_Details": "",
    "LastUpdated": "2026-06-17 15:40:20"
  },
  {
    "Date": "2026-05-15",
    "Year": "2026",
    "Month": "2026-05",
    "SignUps_Accepted": 0,
    "FirstUploads_Accepted": 0,
    "PaidSubscribers_Accepted": 1,
    "SignUp_Details": "",
    "Upload_Details": "",
    "Paid_Details": "planmould@gmail.com <planmould@gmail.com>",
    "LastUpdated": "2026-06-17 15:40:20"
  },
  {
    "Date": "2026-05-17",
    "Year": "2026",
    "Month": "2026-05",
    "SignUps_Accepted": 0,
    "FirstUploads_Accepted": 0,
    "PaidSubscribers_Accepted": 1,
    "SignUp_Details": "",
    "Upload_Details": "",
    "Paid_Details": "NNTC <info@nntc.digital>",
    "LastUpdated": "2026-06-17 15:40:20"
  },
  {
    "Date": "2026-05-18",
    "Year": "2026",
    "Month": "2026-05",
    "SignUps_Accepted": 0,
    "FirstUploads_Accepted": 1,
    "PaidSubscribers_Accepted": 1,
    "SignUp_Details": "",
    "Upload_Details": "lisha <lishaxr2@gmail.com>",
    "Paid_Details": "tools <tools@admindagency.com>",
    "LastUpdated": "2026-06-17 15:40:20"
  },
  {
    "Date": "2026-05-19",
    "Year": "2026",
    "Month": "2026-05",
    "SignUps_Accepted": 0,
    "FirstUploads_Accepted": 2,
    "PaidSubscribers_Accepted": 2,
    "SignUp_Details": "",
    "Upload_Details": "FND_DChilds <dchilds@frankndesign.com>; Piaggio <piaggioconfig20@gmail.com>",
    "Paid_Details": "Piaggio <piaggioconfig20@gmail.com>; Princess <greg@princessyachts.com.au>",
    "LastUpdated": "2026-06-17 15:40:20"
  },
  {
    "Date": "2026-05-20",
    "Year": "2026",
    "Month": "2026-05",
    "SignUps_Accepted": 0,
    "FirstUploads_Accepted": 1,
    "PaidSubscribers_Accepted": 0,
    "SignUp_Details": "",
    "Upload_Details": "eshan122 <mrafshan.tashin@gmail.com>",
    "Paid_Details": "",
    "LastUpdated": "2026-06-17 15:40:20"
  },
  {
    "Date": "2026-05-21",
    "Year": "2026",
    "Month": "2026-05",
    "SignUps_Accepted": 0,
    "FirstUploads_Accepted": 4,
    "PaidSubscribers_Accepted": 1,
    "SignUp_Details": "",
    "Upload_Details": "Sergio <contato@projeviz.com>; Suki <sukisheuyt@gmail.com>; UE5Stream278 <kenjloyd@gmail.com>; huypg1312 <phamgiahuybinh2002@gmail.com>",
    "Paid_Details": "menschlichT <office@menschlicht.eu>",
    "LastUpdated": "2026-06-17 15:40:20"
  },
  {
    "Date": "2026-05-22",
    "Year": "2026",
    "Month": "2026-05",
    "SignUps_Accepted": 0,
    "FirstUploads_Accepted": 2,
    "PaidSubscribers_Accepted": 2,
    "SignUp_Details": "",
    "Upload_Details": "Auzan <auzan.lab@gmail.com>; menschlichT <office@menschlicht.eu>",
    "Paid_Details": "RodrigoConte <rodrigoconte90@gmail.com>; Wavemaker <luiz@thepointsurfpark.com>",
    "LastUpdated": "2026-06-17 15:40:20"
  },
  {
    "Date": "2026-05-25",
    "Year": "2026",
    "Month": "2026-05",
    "SignUps_Accepted": 0,
    "FirstUploads_Accepted": 2,
    "PaidSubscribers_Accepted": 0,
    "SignUp_Details": "",
    "Upload_Details": "artmkrtchyan <artmkrtchyanart@gmail.com>; tools <tools@admindagency.com>",
    "Paid_Details": "",
    "LastUpdated": "2026-06-17 15:40:20"
  },
  {
    "Date": "2026-05-26",
    "Year": "2026",
    "Month": "2026-05",
    "SignUps_Accepted": 0,
    "FirstUploads_Accepted": 1,
    "PaidSubscribers_Accepted": 0,
    "SignUp_Details": "",
    "Upload_Details": "Armin <am2492@cornell.edu>",
    "Paid_Details": "",
    "LastUpdated": "2026-06-17 15:40:20"
  },
  {
    "Date": "2026-05-27",
    "Year": "2026",
    "Month": "2026-05",
    "SignUps_Accepted": 0,
    "FirstUploads_Accepted": 3,
    "PaidSubscribers_Accepted": 1,
    "SignUp_Details": "",
    "Upload_Details": "Sumantbag1992 <trendbysumant@gmail.com>; Syafer <popeyporte2@gmail.com>; Yerassyl <yerassyl.serikbayev@gmail.com>",
    "Paid_Details": "25smithops <25smithops@gmail.com>",
    "LastUpdated": "2026-06-17 15:40:20"
  },
  {
    "Date": "2026-05-28",
    "Year": "2026",
    "Month": "2026-05",
    "SignUps_Accepted": 0,
    "FirstUploads_Accepted": 1,
    "PaidSubscribers_Accepted": 0,
    "SignUp_Details": "",
    "Upload_Details": "amarillaus <pknigge@amarilla.us>",
    "Paid_Details": "",
    "LastUpdated": "2026-06-17 15:40:20"
  },
  {
    "Date": "2026-06-01",
    "Year": "2026",
    "Month": "2026-06",
    "SignUps_Accepted": 3,
    "FirstUploads_Accepted": 3,
    "PaidSubscribers_Accepted": 0,
    "SignUp_Details": "TsaoTaoYung <thor.tt@gmail.com>; naman <naman.devil09@gmail.com>; z9yg4nth3 <z9yg4nth3@mozmail.com>",
    "Upload_Details": "TsaoTaoYung <thor.tt@gmail.com>; naman <naman.devil09@gmail.com>; z9yg4nth3 <z9yg4nth3@mozmail.com>",
    "Paid_Details": "",
    "LastUpdated": "2026-06-17 15:40:20"
  },
  {
    "Date": "2026-06-02",
    "Year": "2026",
    "Month": "2026-06",
    "SignUps_Accepted": 3,
    "FirstUploads_Accepted": 0,
    "PaidSubscribers_Accepted": 1,
    "SignUp_Details": "Abdoulayekane <abdoukane2021@gmail.com>; Evonik_Testuser <evonik_ai_coach@materna.group>; saliou02 <mbiskite12@gmail.com>",
    "Upload_Details": "",
    "Paid_Details": "Juergen Brandt <michael.hennemann@proinspace.de>",
    "LastUpdated": "2026-06-17 15:40:20"
  },
  {
    "Date": "2026-06-03",
    "Year": "2026",
    "Month": "2026-06",
    "SignUps_Accepted": 3,
    "FirstUploads_Accepted": 2,
    "PaidSubscribers_Accepted": 0,
    "SignUp_Details": "Addverb_Business <addverbbusiness@gmail.com>; Anish879 <technicalanish37@gmail.com>; DigitalCanvas <joris.digitalcanvas@gmail.com>",
    "Upload_Details": "Addverb_Business <addverbbusiness@gmail.com>; Anish879 <technicalanish37@gmail.com>",
    "Paid_Details": "",
    "LastUpdated": "2026-06-17 15:40:20"
  },
  {
    "Date": "2026-06-04",
    "Year": "2026",
    "Month": "2026-06",
    "SignUps_Accepted": 3,
    "FirstUploads_Accepted": 1,
    "PaidSubscribers_Accepted": 0,
    "SignUp_Details": "Alex_310 <an2024inbox@gmail.com>; bachwal123 <nikhilbachwal@gmail.com>; khaled <kha306819@gmail.com>",
    "Upload_Details": "bachwal123 <nikhilbachwal@gmail.com>",
    "Paid_Details": "",
    "LastUpdated": "2026-06-17 15:40:20"
  },
  {
    "Date": "2026-06-05",
    "Year": "2026",
    "Month": "2026-06",
    "SignUps_Accepted": 4,
    "FirstUploads_Accepted": 0,
    "PaidSubscribers_Accepted": 0,
    "SignUp_Details": "Aeqism <marisevanvulpen@gmail.com>; MaxLin <agogow5@gmail.com>; SalNouri <contact@salarnouri.com>; sara <sarazaidoon2@gmail.com>",
    "Upload_Details": "",
    "Paid_Details": "",
    "LastUpdated": "2026-06-17 15:40:20"
  },
  {
    "Date": "2026-06-06",
    "Year": "2026",
    "Month": "2026-06",
    "SignUps_Accepted": 1,
    "FirstUploads_Accepted": 2,
    "PaidSubscribers_Accepted": 0,
    "SignUp_Details": "sepanta <sirsepanta@yahoo.com>",
    "Upload_Details": "sepanta <sirsepanta@yahoo.com>; volkanonem35 <volkanonem35@gmail.com>",
    "Paid_Details": "",
    "LastUpdated": "2026-06-17 15:40:20"
  },
  {
    "Date": "2026-06-08",
    "Year": "2026",
    "Month": "2026-06",
    "SignUps_Accepted": 5,
    "FirstUploads_Accepted": 3,
    "PaidSubscribers_Accepted": 0,
    "SignUp_Details": "AgentSykes <stansykes@gmail.com>; kerembaba10 <kerembaba10@gmail.com>; keremermis10 <keremermis10@gmail.com>; keremermis35 <keremermis35@gmail.com>; keremhacettepe <keremermis@hacettepe.edu.tr>",
    "Upload_Details": "kerembaba10 <kerembaba10@gmail.com>; keremermis10 <keremermis10@gmail.com>; keremermis35 <keremermis35@gmail.com>",
    "Paid_Details": "",
    "LastUpdated": "2026-06-17 15:40:20"
  },
  {
    "Date": "2026-06-09",
    "Year": "2026",
    "Month": "2026-06",
    "SignUps_Accepted": 2,
    "FirstUploads_Accepted": 1,
    "PaidSubscribers_Accepted": 1,
    "SignUp_Details": "ArchvizX <hoseina97@gmail.com>; Giorgioadolfo <giorgiokrenkel@gmail.com>",
    "Upload_Details": "Giorgioadolfo <giorgiokrenkel@gmail.com>",
    "Paid_Details": "Perspecto <perspecto.design@gmail.com>",
    "LastUpdated": "2026-06-17 15:40:20"
  },
  {
    "Date": "2026-06-10",
    "Year": "2026",
    "Month": "2026-06",
    "SignUps_Accepted": 17,
    "FirstUploads_Accepted": 1,
    "PaidSubscribers_Accepted": 2,
    "SignUp_Details": "Amirizygs <siaposh45@gmail.com>; Perspecto <perspecto.design@gmail.com>; elifozgecolak2 <elifozgecolak2@gmail.com>; ict01bt <ict01bt@outlook.com>; ict02bt <ict02bt@outlook.com>; ict03bt <ict03bt@outlook.com>; ict04bt <ict04bt@outlook.com>; ict05bt <ict05bt@outlook.com>; ict06bt <ict06bt@outlook.com>; ict07bt <ict07bt@outlook.com>; ict08bt <ict08bt@outlook.com>; ict09bt <ict09bt@outlook.com>; ict10bt <ict10bt@outlook.com>; ictclubst <ictclubst@gmail.com>; parasTheGreat <parassinghme@gmail.com>; robanian <wpql5421@gmail.com>; sadeghi <sadeghi.ghomi@gmail.com>",
    "Upload_Details": "parasTheGreat <parassinghme@gmail.com>",
    "Paid_Details": "archinord <info@archinord.com>; seamus <office@visuallab.ie>",
    "LastUpdated": "2026-06-17 15:40:20"
  },
  {
    "Date": "2026-06-11",
    "Year": "2026",
    "Month": "2026-06",
    "SignUps_Accepted": 6,
    "FirstUploads_Accepted": 4,
    "PaidSubscribers_Accepted": 1,
    "SignUp_Details": "Angela20 <angelamcastrof@gmail.com>; Nalelilepipi <lepipinaleli2@gmail.com>; Yim <jperdomodz@gmail.com>; jdeboer14 <jeffdb1414@gmail.com>; juanpascagasa <juano2505@gmail.com>; nicol038 <nicoldorelyhurtadocortes@gmail.com>",
    "Upload_Details": "Angela20 <angelamcastrof@gmail.com>; Yim <jperdomodz@gmail.com>; jdeboer14 <jeffdb1414@gmail.com>; nicol038 <nicoldorelyhurtadocortes@gmail.com>",
    "Paid_Details": "eagle3d-sense <eagle3d-sense@libelium.com>",
    "LastUpdated": "2026-06-17 15:40:20"
  },
  {
    "Date": "2026-06-12",
    "Year": "2026",
    "Month": "2026-06",
    "SignUps_Accepted": 2,
    "FirstUploads_Accepted": 0,
    "PaidSubscribers_Accepted": 0,
    "SignUp_Details": "Aymen <abedaymen680@gmail.com>; espnta <espantadoublea@gmail.com>",
    "Upload_Details": "",
    "Paid_Details": "",
    "LastUpdated": "2026-06-17 15:40:20"
  },
  {
    "Date": "2026-06-13",
    "Year": "2026",
    "Month": "2026-06",
    "SignUps_Accepted": 4,
    "FirstUploads_Accepted": 2,
    "PaidSubscribers_Accepted": 0,
    "SignUp_Details": "Elgammal <elgammalm071@gmail.com>; SashaLiudkevych <sitw5725@gmail.com>; abdoaymen0046 <elweekel00@gmail.com>; davidinlines <davidinlines@gmail.com>",
    "Upload_Details": "SashaLiudkevych <sitw5725@gmail.com>; abdoaymen0046 <elweekel00@gmail.com>",
    "Paid_Details": "",
    "LastUpdated": "2026-06-17 15:40:20"
  },
  {
    "Date": "2026-06-15",
    "Year": "2026",
    "Month": "2026-06",
    "SignUps_Accepted": 3,
    "FirstUploads_Accepted": 1,
    "PaidSubscribers_Accepted": 2,
    "SignUp_Details": "Elen <elentanlit2000@mail.ru>; arley <arleysign@gmail.com>; frankndesign <office@frankndesign.com>",
    "Upload_Details": "benkerdorf <mr.pipisterrr@gmail.com>",
    "Paid_Details": "frankndesign <office@frankndesign.com>; hello@3dv.academy <hello@3dv.academy>",
    "LastUpdated": "2026-06-17 15:40:20"
  },
  {
    "Date": "2026-06-16",
    "Year": "2026",
    "Month": "2026-06",
    "SignUps_Accepted": 3,
    "FirstUploads_Accepted": 4,
    "PaidSubscribers_Accepted": 0,
    "SignUp_Details": "SalomeRG <salome.ruiz@ebedix.com>; gss <sarmahmisc@gmail.com>; rip <stemgames2000@gmail.com>",
    "Upload_Details": "AgentSykes <stansykes@gmail.com>; davidinlines <davidinlines@gmail.com>; frankndesign <office@frankndesign.com>; rip <stemgames2000@gmail.com>",
    "Paid_Details": "",
    "LastUpdated": "2026-06-17 15:40:20"
  },
  {
    "Date": "2026-06-17",
    "Year": "2026",
    "Month": "2026-06",
    "SignUps_Accepted": 5,
    "FirstUploads_Accepted": 1,
    "PaidSubscribers_Accepted": 0,
    "SignUp_Details": "LiveVitzStudio <cristianadrianmedina@gmail.com>; Rishi_11 <uglyface1909@gmail.com>; _eshwaran_20 <nagarajamutha0@gmail.com>; benkendorf <mr.pipisterrr@gmail.com>; samin <rahmansaminur51@gmail.com>",
    "Upload_Details": "Rishi_11 <uglyface1909@gmail.com>",
    "Paid_Details": "",
    "LastUpdated": "2026-06-17 15:40:20"
  }
]