[
    {"domain": ".linkedin.com", "name": "mbox", "value": "PC#607a1865400245f3aa88ad7f43818dbe.37_0#1795420230|session#1e4cfc56d564488e845177dcaf054c73#1779870090", "path": "/", "secure": true, "httpOnly": false},
    {"domain": ".linkedin.com", "name": "lms_ads", "value": "AQGB3r80x4a3fgAAAZ7taesbw4KhHZFjFVSh04G4lTPFhVVEL51yyAMW0EATtZS821sMchmUABWEy3AHKn8B2u2BhTb1NnqL", "path": "/", "secure": true, "httpOnly": false},
    {"domain": ".linkedin.com", "name": "bcookie", "value": "\"v=2&5e6a1af2-3e04-4ef6-8f73-09e492ec0b42\"", "path": "/", "secure": true, "httpOnly": false},
    {"domain": ".linkedin.com", "name": "lms_analytics", "value": "AQEYogAUo1i5JAAAAZ7taesbGE19gDCFSClqdnOp-f1tYlBD0BKYFFv9lKAgeexGF-zpfl2mWOaF-a3t4xU19kSF9R8o3iIq", "path": "/", "secure": true, "httpOnly": false},
    {"domain": ".www.linkedin.com", "name": "li_at", "value": "AQEDATMgR38CpQGAAAABnu5NVnIAAAGfElnaclYARErhTh3-AYPu0i35bo6kJzEWDw2lu-pWXYPc6-azdSAs-JBb7yhB3CJw4Ky5Lp1GGE3MsrOhIpFBCTSjTezzu54Gx0MDeHwbTs6oJDgPv3B-bdKC", "path": "/", "secure": true, "httpOnly": true},
    {"domain": ".linkedin.com", "name": "lang", "value": "v=2&lang=en-US", "path": "/", "secure": true, "httpOnly": false},
    {"domain": ".linkedin.com", "name": "at_check", "value": "true", "path": "/", "secure": true, "httpOnly": false},
    {"domain": ".linkedin.com", "name": "lidc", "value": "\"b=OB71:s=O:r=O:a=O:p=O:g=3687:u=708:x=1:i=1782114506:t=1782152575:v=2:sig=AQESGz7a3uEIyU_rRf1nJQVRhYwBbOHV\"", "path": "/", "secure": true, "httpOnly": false},
    {"domain": ".linkedin.com", "name": "AnalyticsSyncHistory", "value": "AQLK9ug882TlHwAAAZ7taempUcvGI2iIlkPR50WzZhu3jeDeMr9BDvgrm3zSxAfmvZK7_54GPH3cdeVbXdcJ-A", "path": "/", "secure": true, "httpOnly": false},
    {"domain": ".www.linkedin.com", "name": "bscookie", "value": "\"v=1&2025111014131421632741-113b-4118-82ca-a62deff2775eAQHg32wr5fsuANWKl3RzojDIL77DHLD2\"", "path": "/", "secure": true, "httpOnly": true},
    {"domain": ".www.linkedin.com", "name": "JSESSIONID", "value": "\"ajax:5690378956333271755\"", "path": "/", "secure": true, "httpOnly": false},
    {"domain": ".linkedin.com", "name": "li_sugr", "value": "b29cebf2-7d76-4358-8f46-e3e60fe6606d", "path": "/", "secure": true, "httpOnly": false},
    {"domain": ".www.linkedin.com", "name": "li_theme", "value": "dark", "path": "/", "secure": false, "httpOnly": false},
    {"domain": ".linkedin.com", "name": "UserMatchHistory", "value": "AQKabvzWpiTuQQAAAZ7taemp0p7octI9i9lnL1EjEOirqJt6wwBBLy-dJVpLRTx-2kA1YDn4L0LXYw", "path": "/", "secure": true, "httpOnly": false},
    {"domain": ".www.linkedin.com", "name": "timezone", "value": "Asia/Dhaka", "path": "/", "secure": true, "httpOnly": false}
]
